etncanedge_files/FuncBackedList.py
etncanedge_files/__init__.py
etncanedge_files/_version.py
etncanedge_files/config.py
etncanedge_files/listing.py
etncanedge_files/support/AbstractFileSystemWithBucket.py
etncanedge_files/support/FuncBackedList.py
etncanedge_files/support/LocalFileSystem.py
etncanedge_files/support/RelativeFileSystem.py
etncanedge_files/support/__init__.py
etncanedge_files-0.0.2.dist-info/LICENSE
etncanedge_files-0.0.2.dist-info/METADATA
etncanedge_files-0.0.2.dist-info/WHEEL
etncanedge_files-0.0.2.dist-info/top_level.txt
etncanedge_files-0.0.2.dist-info/RECORD
